esm/__init__.py
esm/pretrained.py
esm/data/ParentChildTreeFile.txt
esm/data/entry_list_safety_29026.list
esm/data/interpro_29026_to_keywords_58641.csv
esm/data/keyword_idf_safety_filtered_58641.npy
esm/data/keyword_vocabulary_safety_filtered_58641.txt
esm/layers/attention.py
esm/layers/blocks.py
esm/layers/codebook.py
esm/layers/ffn.py
esm/layers/geom_attention.py
esm/layers/regression_head.py
esm/layers/rotary.py
esm/layers/structure_proj.py
esm/layers/transformer_stack.py
esm/models/esm3.py
esm/models/esmc.py
esm/models/function_decoder.py
esm/models/vqvae.py
esm/sdk/__init__.py
esm/sdk/api.py
esm/sdk/base_forge_client.py
esm/sdk/experimental.py
esm/sdk/forge.py
esm/sdk/retry.py
esm/sdk/sagemaker.py
esm/sdk/experimental/__init__.py
esm/sdk/experimental/constrained_generation.py
esm/sdk/experimental/guided_generation.py
esm/tokenization/__init__.py
esm/tokenization/function_tokenizer.py
esm/tokenization/residue_tokenizer.py
esm/tokenization/sasa_tokenizer.py
esm/tokenization/sequence_tokenizer.py
esm/tokenization/ss_tokenizer.py
esm/tokenization/structure_tokenizer.py
esm/tokenization/tokenizer_base.py
esm/utils/decoding.py
esm/utils/encoding.py
esm/utils/forge_context_manager.py
esm/utils/generation.py
esm/utils/generation_test.py
esm/utils/misc.py
esm/utils/misc_test.py
esm/utils/noise_schedules.py
esm/utils/parsing.py
esm/utils/residue_constants.py
esm/utils/sampling.py
esm/utils/sampling_test.py
esm/utils/sequential_dataclass.py
esm/utils/system.py
esm/utils/types.py
esm/utils/constants/api.py
esm/utils/constants/esm3.py
esm/utils/constants/models.py
esm/utils/constants/physics.py
esm/utils/function/encode_decode.py
esm/utils/function/interpro.py
esm/utils/function/lsh.py
esm/utils/function/tfidf.py
esm/utils/msa/__init__.py
esm/utils/msa/filter_sequences.py
esm/utils/msa/msa.py
esm/utils/structure/affine3d.py
esm/utils/structure/aligner.py
esm/utils/structure/atom_indexer.py
esm/utils/structure/input_builder.py
esm/utils/structure/metrics.py
esm-3.2.3.dist-info/licenses/LICENSE.md
esm-3.2.3.dist-info/METADATA
esm-3.2.3.dist-info/WHEEL
esm-3.2.3.dist-info/top_level.txt
esm-3.2.3.dist-info/RECORD
