Metadata-Version: 2.4
Name: esm
Version: 3.2.3
Summary: EvolutionaryScale open model repository
Author: EvolutionaryScale Team
Maintainer-email: Zeming Lin <zeming+esm@evolutionaryscale.ai>
Classifier: Development Status :: 3 - Alpha
Classifier: Topic :: Scientific/Engineering :: Bio-Informatics
Classifier: Programming Language :: Python :: 3.12
Requires-Python: <3.13,>=3.12
License-File: LICENSE.md
Requires-Dist: torch>=2.2.0
Requires-Dist: torchvision
Requires-Dist: torchtext
Requires-Dist: transformers<4.48.2
Requires-Dist: ipython
Requires-Dist: einops
Requires-Dist: biotite>=1.0.0
Requires-Dist: msgpack-numpy
Requires-Dist: biopython
Requires-Dist: scikit-learn
Requires-Dist: brotli
Requires-Dist: attrs
Requires-Dist: pandas
Requires-Dist: cloudpathlib
Requires-Dist: httpx
Requires-Dist: tenacity
Requires-Dist: zstd
Requires-Dist: ipywidgets
Requires-Dist: py3dmol
Requires-Dist: pydssp
Requires-Dist: boto3
Requires-Dist: pygtrie
Requires-Dist: dna_features_viewer
Dynamic: license-file
